{
  "project_info": {
    "project_number": "695164154657",
    "project_id": "hackathon-zeladoria",
    "storage_bucket": "hackathon-zeladoria.firebasestorage.app"
  },
  "client": [
    {
      "client_info": {
        "mobilesdk_app_id": "1:695164154657:android:e0035df9bcfd86e6304460",
        "android_client_info": {
          "package_name": "com.hackathon.app"
        }
      },
      "oauth_client": [],
      "api_key": [
        {
          "current_key": "AIzaSyBU7pLC8v7FIQfqgt6iVBru1aNH5V0XmWQ"
        }
      ],
      "services": {
        "appinvite_service": {
          "other_platform_oauth_client": []
        }
      }
    }
  ],
  "configuration_version": "1"
}